khmereasytools/__init__.py
khmereasytools/tools.py
khmereasytools-0.3.7.dist-info/licenses/LICENSE
khmereasytools-0.3.7.dist-info/METADATA
khmereasytools-0.3.7.dist-info/WHEEL
khmereasytools-0.3.7.dist-info/top_level.txt
khmereasytools-0.3.7.dist-info/RECORD
