Metadata-Version: 2.4
Name: khmereasytools
Version: 0.3.7
Summary: A simple, self-contained library for Khmer text processing, with optional OCR and POS tagging support.
Home-page: https://github.com/back-kh/khmereasytools
Author: Nimol Thuon
Author-email: nimol.thuon@gmail.com
Classifier: Programming Language :: Python :: 3
Classifier: License :: OSI Approved :: MIT License
Classifier: Operating System :: OS Independent
Classifier: Topic :: Text Processing :: Linguistic
Requires-Python: >=3.6
License-File: LICENSE
Provides-Extra: ocr
Requires-Dist: pytesseract>=0.3.8; extra == "ocr"
Requires-Dist: Pillow>=9.0.0; extra == "ocr"
Provides-Extra: khmernltk
Requires-Dist: khmernltk>=1.6; extra == "khmernltk"
Provides-Extra: all
Requires-Dist: pytesseract>=0.3.8; extra == "all"
Requires-Dist: Pillow>=9.0.0; extra == "all"
Requires-Dist: khmernltk>=1.6; extra == "all"
Dynamic: author
Dynamic: author-email
Dynamic: classifier
Dynamic: description
Dynamic: description-content-type
Dynamic: home-page
Dynamic: license-file
Dynamic: provides-extra
Dynamic: requires-python
Dynamic: summary
